jdb.py
jsodb-1.6.0.dist-info/LICENSE
jsodb-1.6.0.dist-info/METADATA
jsodb-1.6.0.dist-info/WHEEL
jsodb-1.6.0.dist-info/top_level.txt
jsodb-1.6.0.dist-info/RECORD
