Metadata-Version: 2.1
Name: jsodb
Version: 1.6.0
Summary: simple json database lib
Author-email: dttric <chudinovd222@gmail.com>
Project-URL: Homepage, https://github.com/dttric/jsodb
Project-URL: Bug Tracker, https://github.com/dttric/jsodb/issues
Classifier: Programming Language :: Python :: 3
Classifier: License :: OSI Approved :: MIT License
Classifier: Operating System :: OS Independent
Requires-Python: >=3.7
License-File: LICENSE
